data/__init__.py
data/aws_iam_reference.json
data/iam_reference.py
linter/__init__.py
linter/cli.py
linter/scp_linter.py
scp_lint-0.2.3.dist-info/licenses/LICENSE
scp_lint-0.2.3.dist-info/METADATA
scp_lint-0.2.3.dist-info/WHEEL
scp_lint-0.2.3.dist-info/entry_points.txt
scp_lint-0.2.3.dist-info/top_level.txt
scp_lint-0.2.3.dist-info/RECORD
