Metadata-Version: 2.4
Name: scp-lint
Version: 0.2.3
Summary: A linter for AWS Service Control Policies (SCPs)
Author: OnticX
License-Expression: MIT
Project-URL: Homepage, https://github.com/OnticX/scp-lint
Project-URL: Repository, https://github.com/OnticX/scp-lint
Project-URL: Issues, https://github.com/OnticX/scp-lint/issues
Keywords: aws,scp,iam,linter,security,policy
Classifier: Development Status :: 4 - Beta
Classifier: Intended Audience :: Developers
Classifier: Intended Audience :: System Administrators
Classifier: Operating System :: OS Independent
Classifier: Programming Language :: Python :: 3
Classifier: Programming Language :: Python :: 3.10
Classifier: Programming Language :: Python :: 3.11
Classifier: Programming Language :: Python :: 3.12
Classifier: Topic :: Security
Classifier: Topic :: System :: Systems Administration
Requires-Python: >=3.10
License-File: LICENSE
Requires-Dist: boto3>=1.34.0
Requires-Dist: click>=8.1.0
Requires-Dist: rich>=13.7.0
Requires-Dist: python-dateutil>=2.8.0
Provides-Extra: dev
Requires-Dist: pytest>=7.4.0; extra == "dev"
Requires-Dist: pytest-mock>=3.11.0; extra == "dev"
Requires-Dist: ruff>=0.1.0; extra == "dev"
Requires-Dist: mypy>=1.0.0; extra == "dev"
Dynamic: license-file
